pip_cleanup/__init__.py
pip_cleanup/__main__.py
pip_cleanup/cli.py
pip_cleanup/env_scanner.py
pip_cleanup/scanner.py
pip_cleanup/version.py
pip_cleanup/pipkill/__init__.py
pip_cleanup-0.1.85.dist-info/LICENSE
pip_cleanup-0.1.85.dist-info/METADATA
pip_cleanup-0.1.85.dist-info/WHEEL
pip_cleanup-0.1.85.dist-info/entry_points.txt
pip_cleanup-0.1.85.dist-info/top_level.txt
pip_cleanup-0.1.85.dist-info/RECORD
