Metadata-Version: 2.2
Name: pip-cleanup
Version: 0.1.85
Summary: A Python tool to clean up unused pip packages
Author: Samso9th
License: MIT
Classifier: Programming Language :: Python :: 3
Classifier: License :: OSI Approved :: MIT License
Classifier: Operating System :: OS Independent
Requires-Python: >=3.7
License-File: LICENSE
Requires-Dist: click>=8.0.0
Requires-Dist: colorama>=0.4.4
Requires-Dist: tabulate>=0.8.9
Requires-Dist: setuptools>=75.8.2
Dynamic: author
Dynamic: classifier
Dynamic: description
Dynamic: description-content-type
Dynamic: license
Dynamic: requires-dist
Dynamic: requires-python
Dynamic: summary
